description.md
setup.py
Bullpen/__init__.py
Bullpen/action.py
Bullpen/condition.py
Bullpen/manager.py
Bullpen/transition.py
Bullpen/version.py
Bullpen.egg-info/PKG-INFO
Bullpen.egg-info/SOURCES.txt
Bullpen.egg-info/dependency_links.txt
Bullpen.egg-info/top_level.txt